Metadata-Version: 1.0
Name: pymago
Version: 0.5.0
Summary: CLI Tool for optimizing folder of images
Home-page: https://github.com/gamikun/pymago
Author: Gamaliel Espinoza M.
Author-email: gamaliel.espinoza@gmail.com
License: UNKNOWN
Keywords: magick,optimizer,image,pngquant
Platform: UNKNOWN
